<?xml version = '1.0' encoding = 'UTF-8'?>
<Diagram class="oracle.dbtools.crest.swingui.logical.DPVLogical" name="Logical" id="F58A2F3E-2BE2-8E74-B3A3-7293A620AA48">
<createdBy>edgar</createdBy>
<modifiedBy>edgar</modifiedBy>
<createdTime>2020-08-12 21:07:01 UTC</createdTime>
<autoRoute>false</autoRoute>
<boxInbox>true</boxInbox>
<showLegend>false</showLegend>
<showLabels>false</showLabels>
<showRelAttributes>false</showRelAttributes>
<gridEnabled>false</gridEnabled>
<showGrid>false</showGrid>
<diagramColor>-1</diagramColor>
<display>false</display>
<notation>1</notation>
<objectViews>
<OView class="oracle.dbtools.crest.swingui.logical.TVEntity" oid="112B824F-1194-0628-A03D-846B9FE110C2" otype="Entity" vid="82D57C79-4663-E666-3658-35E34F863AFE">
<hideElementsInCurrentOnly>false</hideElementsInCurrentOnly>
<bounds x="55" y="59" width="170" height="113"/>
</OView>
<OView class="oracle.dbtools.crest.swingui.logical.TVEntity" oid="38CA8E08-37BC-122F-C88C-862B8918C786" otype="Entity" vid="1506F46F-80F0-F7CF-2FFF-7BC255B1C92D">
<hideElementsInCurrentOnly>false</hideElementsInCurrentOnly>
<bounds x="53" y="586" width="170" height="112"/>
</OView>
<OView class="oracle.dbtools.crest.swingui.logical.TVEntity" oid="3F3AD6DA-442D-089E-FA98-BBE1ED01EF78" otype="Entity" vid="5EAEE48C-7FCF-8A77-B10B-C1B6C627A7F4">
<hideElementsInCurrentOnly>false</hideElementsInCurrentOnly>
<bounds x="814" y="53" width="170" height="113"/>
</OView>
<OView class="oracle.dbtools.crest.swingui.logical.TVEntity" oid="4BAB2E8F-FE53-AA2C-4709-5E30C88CD0B8" otype="Entity" vid="5844219A-A092-E402-F196-3CA00C809362">
<hideElementsInCurrentOnly>false</hideElementsInCurrentOnly>
<bounds x="968" y="401" width="170" height="111"/>
</OView>
<OView class="oracle.dbtools.crest.swingui.logical.TVEntity" oid="53CEDFF5-5D7E-2F40-5CBE-34B7022E45D3" otype="Entity" vid="A3AFE587-7E15-4DDD-0220-9D3F96E07504">
<hideElementsInCurrentOnly>false</hideElementsInCurrentOnly>
<bounds x="958" y="229" width="200" height="133"/>
</OView>
<OView class="oracle.dbtools.crest.swingui.logical.TVEntity" oid="59BCCF5C-F2E8-6925-6A40-978B85950589" otype="Entity" vid="196CECD9-EFC6-5D52-6F4B-D07D47B6CC95">
<hideElementsInCurrentOnly>false</hideElementsInCurrentOnly>
<bounds x="700" y="378" width="170" height="111"/>
</OView>
<OView class="oracle.dbtools.crest.swingui.logical.TVEntity" oid="5F282AB3-4B57-F838-A601-A7A040FD7A7B" otype="Entity" vid="19E23C9A-7A99-A18A-9001-186E123F2C60">
<hideElementsInCurrentOnly>false</hideElementsInCurrentOnly>
<bounds x="404" y="618" width="170" height="113"/>
</OView>
<OView class="oracle.dbtools.crest.swingui.logical.TVEntity" oid="5FA65DB6-B3D4-8164-367E-17888272BB08" otype="Entity" vid="14354098-5DB7-C412-EA04-0FB5D68F5D91">
<hideElementsInCurrentOnly>false</hideElementsInCurrentOnly>
<bounds x="797" y="568" width="188" height="142"/>
</OView>
<OView class="oracle.dbtools.crest.swingui.logical.TVEntity" oid="7E2799A5-8EE0-0BDA-1991-AF1CB0D2FB6B" otype="Entity" vid="926B664E-3DD7-C4B3-E77C-046B9CB32238">
<hideElementsInCurrentOnly>false</hideElementsInCurrentOnly>
<bounds x="377" y="30" width="170" height="153"/>
</OView>
<OView class="oracle.dbtools.crest.swingui.logical.TVEntity" oid="88E302A2-94F5-F0A5-0DEA-77C7EE5524CE" otype="Entity" vid="2FC58341-B295-96E3-9E6E-7A5AF1DD7971">
<hideElementsInCurrentOnly>false</hideElementsInCurrentOnly>
<bounds x="56" y="334" width="170" height="113"/>
</OView>
<OView class="oracle.dbtools.crest.swingui.logical.TVEntity" oid="F73021CC-C313-2BFB-59CC-8E7CE0A01DEF" otype="Entity" vid="289335A8-EF5D-0DC5-A6B7-DE78F88D9DA7">
<hideElementsInCurrentOnly>false</hideElementsInCurrentOnly>
<bounds x="400" y="313" width="170" height="113"/>
</OView>
</objectViews>
<connectors>
<Connector class="oracle.dbtools.crest.swingui.logical.TVRelation" oid="074A6C43-3C81-9AEA-005A-47ED37D738AD" otype="Relation" vid_source="196CECD9-EFC6-5D52-6F4B-D07D47B6CC95" vid_target="289335A8-EF5D-0DC5-A6B7-DE78F88D9DA7">
<hideElementsInCurrentOnly>false</hideElementsInCurrentOnly>
<backgroundColor>-16777216</backgroundColor>
<lineWidth>1</lineWidth>
<points>
<point x="700" y="402"/>
<point x="570" y="402"/>
</points>
</Connector>
<Connector class="oracle.dbtools.crest.swingui.logical.TVRelation" oid="0C234FF5-C6AA-C4BF-0FC7-E6434C82163D" otype="Relation" vid_source="196CECD9-EFC6-5D52-6F4B-D07D47B6CC95" vid_target="5844219A-A092-E402-F196-3CA00C809362">
<hideElementsInCurrentOnly>false</hideElementsInCurrentOnly>
<backgroundColor>-16777216</backgroundColor>
<lineWidth>1</lineWidth>
<points>
<point x="870" y="445"/>
<point x="968" y="445"/>
</points>
</Connector>
<Connector class="oracle.dbtools.crest.swingui.logical.TVRelation" oid="229EBAD6-8B9F-24F8-2FFD-44A2480CF468" otype="Relation" vid_source="5EAEE48C-7FCF-8A77-B10B-C1B6C627A7F4" vid_target="926B664E-3DD7-C4B3-E77C-046B9CB32238">
<hideElementsInCurrentOnly>false</hideElementsInCurrentOnly>
<backgroundColor>-16777216</backgroundColor>
<lineWidth>1</lineWidth>
<points>
<point x="814" y="109"/>
<point x="547" y="109"/>
</points>
</Connector>
<Connector class="oracle.dbtools.crest.swingui.logical.TVRelation" oid="4A1B8FA3-55CD-8FF3-A78E-5CAB0682F811" otype="Relation" vid_source="2FC58341-B295-96E3-9E6E-7A5AF1DD7971" vid_target="82D57C79-4663-E666-3658-35E34F863AFE">
<hideElementsInCurrentOnly>false</hideElementsInCurrentOnly>
<backgroundColor>-16777216</backgroundColor>
<lineWidth>1</lineWidth>
<points>
<point x="140" y="334"/>
<point x="140" y="172"/>
</points>
</Connector>
<Connector class="oracle.dbtools.crest.swingui.logical.TVRelation" oid="52544BE1-9D09-1DCD-007D-0A11F1712620" otype="Relation" vid_source="289335A8-EF5D-0DC5-A6B7-DE78F88D9DA7" vid_target="19E23C9A-7A99-A18A-9001-186E123F2C60">
<hideElementsInCurrentOnly>false</hideElementsInCurrentOnly>
<backgroundColor>-16777216</backgroundColor>
<lineWidth>1</lineWidth>
<points>
<point x="487" y="426"/>
<point x="487" y="618"/>
</points>
</Connector>
<Connector class="oracle.dbtools.crest.swingui.logical.TVRelation" oid="549A59C0-FEFA-AEC0-DE79-6138834F0DEF" otype="Relation" vid_source="289335A8-EF5D-0DC5-A6B7-DE78F88D9DA7" vid_target="926B664E-3DD7-C4B3-E77C-046B9CB32238">
<hideElementsInCurrentOnly>false</hideElementsInCurrentOnly>
<backgroundColor>-16777216</backgroundColor>
<lineWidth>1</lineWidth>
<points>
<point x="473" y="313"/>
<point x="473" y="183"/>
</points>
</Connector>
<Connector class="oracle.dbtools.crest.swingui.logical.TVRelation" oid="6B84C6A3-7D32-253F-D3EE-07D3B210046B" otype="Relation" vid_source="5EAEE48C-7FCF-8A77-B10B-C1B6C627A7F4" vid_target="A3AFE587-7E15-4DDD-0220-9D3F96E07504">
<hideElementsInCurrentOnly>false</hideElementsInCurrentOnly>
<backgroundColor>-16777216</backgroundColor>
<lineWidth>1</lineWidth>
<points>
<point x="971" y="166"/>
<point x="971" y="229"/>
</points>
</Connector>
<Connector class="oracle.dbtools.crest.swingui.logical.TVRelation" oid="78061D8D-CB4A-78E1-0555-423A228D5497" otype="Relation" vid_source="289335A8-EF5D-0DC5-A6B7-DE78F88D9DA7" vid_target="5EAEE48C-7FCF-8A77-B10B-C1B6C627A7F4">
<hideElementsInCurrentOnly>false</hideElementsInCurrentOnly>
<backgroundColor>-16777216</backgroundColor>
<lineWidth>1</lineWidth>
<points>
<point x="570" y="316"/>
<point x="814" y="162"/>
</points>
</Connector>
<Connector class="oracle.dbtools.crest.swingui.logical.TVRelation" oid="9BAABB91-123D-0546-FC5C-C6972BB16BEF" otype="Relation" vid_source="289335A8-EF5D-0DC5-A6B7-DE78F88D9DA7" vid_target="1506F46F-80F0-F7CF-2FFF-7BC255B1C92D">
<hideElementsInCurrentOnly>false</hideElementsInCurrentOnly>
<backgroundColor>-16777216</backgroundColor>
<lineWidth>1</lineWidth>
<points>
<point x="413" y="426"/>
<point x="209" y="586"/>
</points>
</Connector>
<Connector class="oracle.dbtools.crest.swingui.logical.TVRelation" oid="A499B22C-297C-22F7-F519-7AC40B9DF03D" otype="Relation" vid_source="2FC58341-B295-96E3-9E6E-7A5AF1DD7971" vid_target="289335A8-EF5D-0DC5-A6B7-DE78F88D9DA7">
<hideElementsInCurrentOnly>false</hideElementsInCurrentOnly>
<backgroundColor>-16777216</backgroundColor>
<lineWidth>1</lineWidth>
<points>
<point x="226" y="380"/>
<point x="400" y="380"/>
</points>
</Connector>
<Connector class="oracle.dbtools.crest.swingui.logical.TVRelation" oid="CB112354-BFDF-6FA9-304A-72A84664FCC2" otype="Relation" vid_source="19E23C9A-7A99-A18A-9001-186E123F2C60" vid_target="14354098-5DB7-C412-EA04-0FB5D68F5D91">
<hideElementsInCurrentOnly>false</hideElementsInCurrentOnly>
<backgroundColor>-16777216</backgroundColor>
<lineWidth>1</lineWidth>
<points>
<point x="574" y="664"/>
<point x="797" y="664"/>
</points>
</Connector>
<Connector class="oracle.dbtools.crest.swingui.logical.TVRelation" oid="D953F482-3F59-5932-BE7F-DEEB0F16F367" otype="Relation" vid_source="289335A8-EF5D-0DC5-A6B7-DE78F88D9DA7" vid_target="82D57C79-4663-E666-3658-35E34F863AFE">
<hideElementsInCurrentOnly>false</hideElementsInCurrentOnly>
<backgroundColor>-16777216</backgroundColor>
<lineWidth>1</lineWidth>
<points>
<point x="408" y="313"/>
<point x="216" y="172"/>
</points>
</Connector>
</connectors>
</Diagram>
